topsis/__init__.py
topsis/__main__.py
Topsis_Mannat_102003288-1.0.0.dist-info/LICENSE
Topsis_Mannat_102003288-1.0.0.dist-info/METADATA
Topsis_Mannat_102003288-1.0.0.dist-info/WHEEL
Topsis_Mannat_102003288-1.0.0.dist-info/entry_points.txt
Topsis_Mannat_102003288-1.0.0.dist-info/top_level.txt
Topsis_Mannat_102003288-1.0.0.dist-info/RECORD
