Metadata-Version: 2.1
Name: Topsis-Mannat-102003288
Version: 1.0.0
Summary: A Python package implementing TOPSIS technique.
Home-page: 
Author: Mannat Randhawa
Author-email: mannat23032002@gmail.com
License: MIT
Classifier: License :: OSI Approved :: MIT License
Classifier: Programming Language :: Python :: 3
Classifier: Programming Language :: Python :: 3.7
License-File: LICENSE
Requires-Dist: numpy
Requires-Dist: pandas
